injector_collections/Collection.py
injector_collections/CollectionItem.py
injector_collections/Generator.py
injector_collections/__init__.py
injector_collections/collection.jinja
injector_collections/constants.py
injector_collections-0.1.0.dist-info/METADATA
injector_collections-0.1.0.dist-info/WHEEL
injector_collections-0.1.0.dist-info/licenses/LICENSE
injector_collections-0.1.0.dist-info/RECORD
