Metadata-Version: 2.4
Name: injector_collections
Version: 0.1.0
Summary: Collections for the Injector Package
Project-URL: Homepage, https://github.com/bschnitz/injector_collections
Project-URL: Issues, https://github.com/bschnitz/injector_collections/issues
Author-email: Benjamin Schnitzler <regenbogenbauer@web.de>
License-File: LICENSE
Classifier: License :: OSI Approved :: MIT License
Classifier: Operating System :: OS Independent
Classifier: Programming Language :: Python :: 3
Requires-Python: >=3.12
Requires-Dist: injector>=0.21.0
Requires-Dist: jinja2>=3.1
